{
  "project_info": {
    "project_number": "863641382611",
    "project_id": "cooker-app-2024",
    "storage_bucket": "cooker-app-2024.appspot.com"
  },
  "client": [
    {
      "client_info": {
        "mobilesdk_app_id": "1:863641382611:android:2118232a2b476e2a886e26",
        "android_client_info": {
          "package_name": "com.example.cooker_app"
        }
      },
      "oauth_client": [],
      "api_key": [
        {
          "current_key": "AIzaSyB0hrjBToAtIE44J7Zl6joYoy6jGbugmL0"
        }
      ],
      "services": {
        "appinvite_service": {
          "other_platform_oauth_client": []
        }
      }
    }
  ],
  "configuration_version": "1"
}